perceptron_pypi_package/__init__.py
perceptron_pypi_package/perceptron.py
pypi_package_creation_arjunaju123-0.0.4.dist-info/LICENSE
pypi_package_creation_arjunaju123-0.0.4.dist-info/METADATA
pypi_package_creation_arjunaju123-0.0.4.dist-info/WHEEL
pypi_package_creation_arjunaju123-0.0.4.dist-info/top_level.txt
pypi_package_creation_arjunaju123-0.0.4.dist-info/RECORD
