Metadata-Version: 2.1
Name: pypi-package-creation-arjunaju123
Version: 0.0.4
Summary: It's an implementation of perceptron
Home-page: https://github.com/arjunaju123/pypi_package_creation
Author: arjunaju123
Author-email: 54721arjun@gmail.com
License: UNKNOWN
Project-URL: Bug Tracker, https://github.com/arjunaju123/pypi_package_creation/issues
Platform: UNKNOWN
Classifier: Programming Language :: Python :: 3
Classifier: License :: OSI Approved :: MIT License
Classifier: Operating System :: OS Independent
Requires-Python: >=3.7
License-File: LICENSE
Requires-Dist: numpy
Requires-Dist: tqdm
